addon_system/__init__.py
addon_system/errors.py
addon_system/make_addon.py
addon_system/utils.py
addon_system/addon/__init__.py
addon_system/addon/addon.py
addon_system/addon/builder.py
addon_system/addon/interface.py
addon_system/addon/meta.py
addon_system/addon/namespace.py
addon_system/addon/storage.py
addon_system/libraries/__init__.py
addon_system/libraries/base_manager.py
addon_system/libraries/pip_manager.py
addon_system/system/__init__.py
addon_system/system/storage.py
addon_system/system/system.py
addon_system-1.2.20.dist-info/LICENSE
addon_system-1.2.20.dist-info/METADATA
addon_system-1.2.20.dist-info/WHEEL
addon_system-1.2.20.dist-info/entry_points.txt
addon_system-1.2.20.dist-info/top_level.txt
addon_system-1.2.20.dist-info/RECORD
