Metadata-Version: 2.1
Name: addon-system
Version: 1.2.20
Summary: The AddonSystem library
Author-email: KuyuGama <mail.kuyugama@gmail.com>
License: GNU GENERAL PUBLIC LICENSE
Project-URL: homepage, https://github.com/kuyugama/addon-system
Classifier: Programming Language :: Python :: 3
Requires-Python: >=3.9
License-File: LICENSE
Provides-Extra: baked
Requires-Dist: pybaked==0.0.15; extra == "baked"
